README.md
setup.py
GrpcFileSystem.egg-info/PKG-INFO
GrpcFileSystem.egg-info/SOURCES.txt
GrpcFileSystem.egg-info/dependency_links.txt
GrpcFileSystem.egg-info/requires.txt
GrpcFileSystem.egg-info/top_level.txt
NASFileGrpcSystem/__init__.py
NASFileGrpcSystem/code_dict.py
NASFileGrpcSystem/grpc_copy_move_file.py
NASFileGrpcSystem/grpc_create_file.py
NASFileGrpcSystem/grpc_describe_file.py
NASFileGrpcSystem/grpc_modify_file.py
NASFileGrpcSystem/proto/__init__.py
NASFileGrpcSystem/proto/files_pb2.py
NASFileGrpcSystem/proto/files_pb2_grpc.py