Metadata-Version: 1.1
Name: GrpcFileSystem
Version: 1.1.0
Summary: A python file handler use Grpc client. It used to handle ctec file work, and include: upload and download file from remote, modify file name, copy and move file.
Home-page: UNKNOWN
Author: Kepner Wu
Author-email: kepner_wu@hotmail.com
License: MIT
Keywords: CTEC NAS file Grpc system includes create file,get file describe,modify,copy and move file
Platform: all
Classifier: Development Status :: 4 - Beta
Classifier: Intended Audience :: Developers
Classifier: Topic :: Software Development :: Libraries
Classifier: License :: OSI Approved :: MIT License
Classifier: Programming Language :: Python :: 2.7
Classifier: Programming Language :: Python :: 3.5
Classifier: Programming Language :: Python :: 3.6
Classifier: Programming Language :: Python :: 3.7
